clonepulse/__about__.py
clonepulse/__init__.py
clonepulse/fetch_clones.py
clonepulse/generate_clone_dashboard.py
clonepulse/util.py
clonepulse-1.0.5.dist-info/METADATA
clonepulse-1.0.5.dist-info/WHEEL
clonepulse-1.0.5.dist-info/licenses/LICENSE
clonepulse-1.0.5.dist-info/RECORD
