Metadata-Version: 2.4
Name: clonepulse
Version: 1.0.5
Summary: Your GitHub clone stats, visualized and celebrated.
Project-URL: Homepage, https://github.com/per2jensen/clonepulse
Project-URL: Issues, https://github.com/per2jensen/clonepulse/issues
Author-email: Per Jensen <clonepulse@pm.me>
License: MIT License
License-File: LICENSE
Classifier: Development Status :: 4 - Beta
Classifier: Intended Audience :: End Users/Desktop
Classifier: License :: OSI Approved :: MIT License
Classifier: Operating System :: POSIX :: Linux
Classifier: Programming Language :: Python :: 3.9
Requires-Python: >=3.9
Requires-Dist: matplotlib>=3.10.3
Requires-Dist: pandas>=2.3.0
Requires-Dist: requests>=2.32.2
Provides-Extra: dev
Requires-Dist: coverage>=7.8.2; extra == 'dev'
Requires-Dist: matplotlib>=3.10.3; extra == 'dev'
Requires-Dist: pandas>=2.3.0; extra == 'dev'
Requires-Dist: pytest; extra == 'dev'
Requires-Dist: pytest-cov>=6.1.1; extra == 'dev'
Requires-Dist: pytest>=8.4.0; extra == 'dev'
Requires-Dist: requests>=2.32.2; extra == 'dev'
Requires-Dist: wheel>=0.45.1; extra == 'dev'
Provides-Extra: packaging
Requires-Dist: build>=1.2.2; extra == 'packaging'
Requires-Dist: hatch>=1.14.1; extra == 'packaging'
Requires-Dist: hatchling>=1.27.0; extra == 'packaging'
Requires-Dist: twine>=6.1.0; extra == 'packaging'
